meODIN/__init__.py
meODIN/auth.py
meODIN/core.py
meODIN/decorators.py
meODIN/module1.py
meODIN/module2.py
meODIN-0.1.0.dist-info/METADATA
meODIN-0.1.0.dist-info/WHEEL
meODIN-0.1.0.dist-info/top_level.txt
meODIN-0.1.0.dist-info/RECORD
