Metadata-Version: 2.1
Name: meODIN
Version: 0.1.0
Summary: Optical Design Integrated Network
Author: Sebastian Gedeon
Author-email: sebastian.gedeon@gmail.com
License: MIT
Classifier: License :: OSI Approved :: MIT License
Classifier: Programming Language :: Python :: 3
Classifier: Operating System :: OS Independent
Requires-Python: >=3.7
Requires-Dist: requests
